infinstor/__init__.py
infinstor/bootstrap.py
infinstor/gnode.py
infinstor/infin_ast.py
infinstor/infin_boto3.py
infinstor/infin_files_meta.py
infinstor/mlflow_run.py
infinstor/tokenfile.py
infinstor/utils.py
infinstor/infinfs/__init__.py
infinstor/infinfs/infin_download.py
infinstor/infinfs/infin_prefetch.py
infinstor/infinfs/infinfs.py
infinstor/infinfs/infinmount.py
infinstor-2.1.3.dist-info/LICENSE
infinstor-2.1.3.dist-info/METADATA
infinstor-2.1.3.dist-info/WHEEL
infinstor-2.1.3.dist-info/top_level.txt
infinstor-2.1.3.dist-info/RECORD
