Metadata-Version: 2.1
Name: infinstor
Version: 2.1.3
Summary: InfinStor Utilities usually run in ipython from jupyterlab cells
Home-page: https://infinstor.com/
Author: InfinStor, Inc.
Author-email: support@infinstor.com
License: AGPL-3.0
Classifier: Programming Language :: Python :: 3
Classifier: License :: OSI Approved :: GNU Affero General Public License v3 or later (AGPLv3+)
Classifier: Operating System :: OS Independent
Requires-Python: >=3.6
License-File: LICENSE
Requires-Dist: boto3
Requires-Dist: pandas
Requires-Dist: tqdm
Requires-Dist: astor
Requires-Dist: jsons
Requires-Dist: fusepy
Requires-Dist: xmltodict
Requires-Dist: traceback-with-variables
